h5xp_extractor/__init__.py
h5xp_extractor/h5xp_extractor.py
h5xp_extractor-0.1.0.dist-info/LICENSE
h5xp_extractor-0.1.0.dist-info/METADATA
h5xp_extractor-0.1.0.dist-info/WHEEL
h5xp_extractor-0.1.0.dist-info/top_level.txt
h5xp_extractor-0.1.0.dist-info/RECORD
