Metadata-Version: 2.1
Name: h5xp_extractor
Version: 0.1.0
Summary: A script to extract waves from an Igor Pro 8 or later .h5xp file
Author-email: Evangelos Golias <evangelos.golias@gmail.com>
Project-URL: Homepage, https://gitlab.com/evangelosgolias/athina
Project-URL: Issues, https://gitlab.com/evangelosgolias/athina/-/issues
Classifier: Programming Language :: Python :: 3
Classifier: License :: OSI Approved :: MIT License
Classifier: Operating System :: OS Independent
Requires-Python: >=3.8
License-File: LICENSE
